radar/Client.py
radar/__init__.py
radarbots.py-0.0.4.dist-info/LICENSE
radarbots.py-0.0.4.dist-info/METADATA
radarbots.py-0.0.4.dist-info/WHEEL
radarbots.py-0.0.4.dist-info/top_level.txt
radarbots.py-0.0.4.dist-info/RECORD
