Metadata-Version: 2.1
Name: radarbots.py
Version: 0.0.4
Summary: An unofficial package to interact with the Radar Bot Directory API
Author: Yoshiboi18303 (Brice Coley)
Author-email: <yoshiboi18303.t@gmail.com>
License: UNKNOWN
Keywords: python,discord,radarbotdirectory
Platform: UNKNOWN
Classifier: Development Status :: 1 - Planning
Classifier: Intended Audience :: Developers
Classifier: Programming Language :: Python :: 3
Classifier: Operating System :: Unix
Classifier: Operating System :: MacOS :: MacOS X
Classifier: Operating System :: Microsoft :: Windows
License-File: LICENSE
Requires-Dist: discord.py
Requires-Dist: requests
